Metadata-Version: 2.1
Name: logitol
Version: 0.1.0.0
Summary: DO NOT USE - This is a beta package
Home-page: https://gitlab.com/hashmapinc/oss/logitol
Author: John Aven
Author-email: accelerators@hashmapinc.com
License: UNKNOWN
Platform: UNKNOWN
Classifier: Programming Language :: Python :: 3
Classifier: License :: OSI Approved :: Apache Software License
Classifier: Operating System :: OS Independent
Classifier: Development Status :: 4 - Beta
Requires-Python: >=3.6
